quickchart/__init__.py
quickchart.io-1.0.1.dist-info/LICENSE
quickchart.io-1.0.1.dist-info/WHEEL
quickchart.io-1.0.1.dist-info/METADATA
quickchart.io-1.0.1.dist-info/RECORD
