Metadata-Version: 2.1
Name: quickchart.io
Version: 1.0.1
Summary: A client for quickchart.io, a service that generates static chart images
Home-page: https://quickchart.io/
License: MIT
Keywords: chart api,chart image,charts
Author: Ian Webster
Author-email: ianw_pypi@ianww.com
Maintainer: Ian Webster
Maintainer-email: ianw_pypi@ianww.com
Requires-Python: >=2.7, !=3.0.*, !=3.1.*, !=3.2.*, !=3.3.*, !=3.4.*
Classifier: License :: OSI Approved :: MIT License
Classifier: Programming Language :: Python :: 2
Classifier: Programming Language :: Python :: 2.7
Classifier: Programming Language :: Python :: 3
Classifier: Programming Language :: Python :: 3.5
Classifier: Programming Language :: Python :: 3.6
Classifier: Programming Language :: Python :: 3.7
Classifier: Programming Language :: Python :: 3.8
Requires-Dist: requests (>=2.23.0,<3.0.0)
Project-URL: Repository, https://github.com/typpo/quickchart-python
